mso_tools/mso_base.py
mso_tools/mso_outlook_mail.py
mso_tools/mso_sharepoint.py
Office365_Wrapper-1.0.0.dist-info/LICENSE
Office365_Wrapper-1.0.0.dist-info/METADATA
Office365_Wrapper-1.0.0.dist-info/WHEEL
Office365_Wrapper-1.0.0.dist-info/top_level.txt
Office365_Wrapper-1.0.0.dist-info/RECORD
